<?xml version="1.0" encoding="UTF-8"?>
 
<!-- Siempre las lineas xml van a ir delimitados por la etiqueta openerp-->
<openerp>
        <!-- Las etiquetas data tambien delimitan a las record siempre -->
        <data>
                <!-- La etiqueta record son la que permitiran mostrar el campo color en el formulario producto-->
                <record model='ir.ui.view' id='product_importancia_form_view'>
                        <field name='name'>product.form.importancia</field>
                        <field name='model'>product.product</field>
                        <field name='inherit_id' ref='product.product_normal_form_view'/>
                        <field name='type'>form</field>
                        <field name='arch' type='xml'>
                                <field name="cost_method" position="after"> <!-- after: despues del campo list_price -->
                                        <field name="importancia"/>
                                </field>
                                
                        </field>
 
                </record>
                
                <record model='ir.ui.view' id='product_importancia_form_view_2'>
                        <field name='name'>product.form.importancia</field>
                        <field name='model'>product.product</field>
                        <field name='inherit_id' ref='product.product_normal_form_view'/>
                        <field name='type'>form</field>
                        <field name='arch' type='xml'>
                                <field name="state" position="replace">
                                        <field name="state_property"/>
                                </field>
                        </field>
                </record>
                
                <record model='ir.ui.view' id='product_importancia_form_view_3'>
                        <field name='name'>product.tree.importancia</field>
                        <field name='model'>product.product</field>
                        <field name='inherit_id' ref='product.product_product_tree_view'/>
                        <field name='type'>tree</field>
                        <field name='arch' type='xml'>
                                <field name="state" position= 'attributes'>
                                        <attribute name="invisible">1</attribute>
                                </field>
                                <field name="state" position="after">
                                        <field name="state_property"/>
                                </field>
                        </field>
                </record>
                

        </data>
</openerp>
